ai_trader/__init__.py
ai_trader/cli.py
ai_trader/utils.py
ai_trader/backtesting/__init__.py
ai_trader/backtesting/feeds/__init__.py
ai_trader/backtesting/strategies/__init__.py
ai_trader/backtesting/strategies/base.py
ai_trader/backtesting/strategies/indicators.py
ai_trader/backtesting/strategies/classic/__init__.py
ai_trader/backtesting/strategies/classic/adaptive_rsi.py
ai_trader/backtesting/strategies/classic/alpharsi_pro.py
ai_trader/backtesting/strategies/classic/bbands.py
ai_trader/backtesting/strategies/classic/buyhold.py
ai_trader/backtesting/strategies/classic/double_top.py
ai_trader/backtesting/strategies/classic/hybrid_alpharsi.py
ai_trader/backtesting/strategies/classic/macd.py
ai_trader/backtesting/strategies/classic/momentum.py
ai_trader/backtesting/strategies/classic/risk_averse.py
ai_trader/backtesting/strategies/classic/roc.py
ai_trader/backtesting/strategies/classic/rsi.py
ai_trader/backtesting/strategies/classic/rsrs.py
ai_trader/backtesting/strategies/classic/sma.py
ai_trader/backtesting/strategies/classic/turtle.py
ai_trader/backtesting/strategies/classic/vcp.py
ai_trader/backtesting/strategies/portfolio/__init__.py
ai_trader/backtesting/strategies/portfolio/multi_bbands.py
ai_trader/backtesting/strategies/portfolio/roc_rotation.py
ai_trader/backtesting/strategies/portfolio/rsrs_rotation.py
ai_trader/backtesting/strategies/portfolio/triple_rsi.py
ai_trader/core/__init__.py
ai_trader/core/config.py
ai_trader/core/exceptions.py
ai_trader/core/logging.py
ai_trader/core/utils.py
ai_trader/data/__init__.py
ai_trader/data/fetchers/__init__.py
ai_trader/data/fetchers/base.py
ai_trader/data/fetchers/crypto.py
ai_trader/data/fetchers/forex.py
ai_trader/data/fetchers/tw_stock.py
ai_trader/data/fetchers/us_stock.py
ai_trader/data/fetchers/vix.py
ai_trader/data/storage/__init__.py
ai_trader/data/storage/base.py
ai_trader/mcp/__init__.py
ai_trader/mcp/__main__.py
ai_trader/mcp/models.py
ai_trader/mcp/server.py
ai_trader/mcp/tools/__init__.py
ai_trader-0.3.3.dist-info/licenses/LICENSE
ai_trader-0.3.3.dist-info/METADATA
ai_trader-0.3.3.dist-info/WHEEL
ai_trader-0.3.3.dist-info/entry_points.txt
ai_trader-0.3.3.dist-info/top_level.txt
ai_trader-0.3.3.dist-info/RECORD
