Metadata-Version: 2.4
Name: ai-trader
Version: 0.3.3
Summary: Backtrader-powered backtesting framework for algorithmic trading, featuring 20+ strategies, multi-market support, CLI tools, and an integrated MCP server for professional traders.
Author-email: Will Chien <locriginal@gmail.com>
License: GPL-3.0
Project-URL: Homepage, https://github.com/whchien/ai-trader
Project-URL: Documentation, https://ai-trader.readthedocs.io
Project-URL: Repository, https://github.com/whchien/ai-trader
Project-URL: Issues, https://github.com/whchien/ai-trader/issues
Keywords: backtesting,algorithmic-trading,finance,backtrader,technical-analysis,mcp,cli,quantitative-finance
Classifier: Development Status :: 4 - Beta
Classifier: Intended Audience :: Developers
Classifier: Intended Audience :: Financial and Insurance Industry
Classifier: Topic :: Office/Business :: Financial :: Investment
Classifier: License :: OSI Approved :: GNU General Public License v3 or later (GPLv3+)
Classifier: Programming Language :: Python :: 3
Classifier: Programming Language :: Python :: 3.11
Classifier: Programming Language :: Python :: 3.12
Classifier: Programming Language :: Python :: 3.13
Classifier: Operating System :: OS Independent
Requires-Python: <4.0,>=3.11
License-File: LICENSE
Requires-Dist: backtrader==1.9.78.123
Requires-Dist: pandas<3.0.0,>=2.0.0
Requires-Dist: numpy<2.0.0,>=1.24.0
Requires-Dist: matplotlib<4.0.0,>=3.7.0
Requires-Dist: yfinance>=0.2.0
Requires-Dist: twstock>=1.4.0
Requires-Dist: TA-Lib>=0.4.0
Requires-Dist: statsmodels>=0.14.0
Requires-Dist: scipy>=1.10.0
Requires-Dist: lxml>=5.2.2
Requires-Dist: click>=8.0.0
Requires-Dist: pydantic>=2.0.0
Requires-Dist: pyyaml>=6.0.0
Requires-Dist: requests>=2.32.4
Requires-Dist: fastmcp>=2.0.0
Provides-Extra: dev
Requires-Dist: pytest>=7.0.0; extra == "dev"
Requires-Dist: pytest-cov>=4.0.0; extra == "dev"
Requires-Dist: pytest-mock>=3.10.0; extra == "dev"
Requires-Dist: pytest-benchmark>=4.0.0; extra == "dev"
Requires-Dist: mypy>=1.0.0; extra == "dev"
Requires-Dist: ruff>=0.4.8; extra == "dev"
Requires-Dist: pre-commit>=3.0.0; extra == "dev"
Requires-Dist: types-pyyaml>=6.0.0; extra == "dev"
Requires-Dist: types-requests>=2.31.0; extra == "dev"
Requires-Dist: bandit>=1.7.0; extra == "dev"
Requires-Dist: pip-audit>=2.6.0; extra == "dev"
Provides-Extra: docs
Requires-Dist: sphinx>=7.0.0; extra == "docs"
Requires-Dist: sphinx-rtd-theme>=1.3.0; extra == "docs"
Requires-Dist: sphinx-autodoc-typehints>=1.24.0; extra == "docs"
Provides-Extra: notebook
Requires-Dist: jupyter>=1.0.0; extra == "notebook"
Requires-Dist: nbval>=0.10.0; extra == "notebook"
Requires-Dist: ipykernel>=6.25.0; extra == "notebook"
Dynamic: license-file
